trustspecgen/__init__.py
trustspecgen/main.py
trustspecgen-0.1.0.dist-info/METADATA
trustspecgen-0.1.0.dist-info/WHEEL
trustspecgen-0.1.0.dist-info/entry_points.txt
trustspecgen-0.1.0.dist-info/RECORD
