Metadata-Version: 2.1
Name: trustspecgen
Version: 0.1.0
Summary: 
Author: Wojciech Karwacki
Author-email: karwacki.wojciech@gmail.com
Requires-Python: >=3.10,<4.0
Classifier: Programming Language :: Python :: 3
Classifier: Programming Language :: Python :: 3.10
Classifier: Programming Language :: Python :: 3.11
Classifier: Programming Language :: Python :: 3.12
Requires-Dist: trustspecpy (==0.1.0)
